Metadata-Version: 2.1
Name: nwon_deployment
Version: 0.1.24
Summary: Helper for deployment and CI scripts
Home-page: https://nwon.de
License: MIT
Author: Reik Stiebeling
Author-email: reik.stiebeling@nwon.de
Requires-Python: >=3.8,<4.0
Classifier: License :: OSI Approved :: MIT License
Classifier: Programming Language :: Python :: 3
Classifier: Programming Language :: Python :: 3.8
Classifier: Programming Language :: Python :: 3.9
Classifier: Programming Language :: Python :: 3.10
Classifier: Programming Language :: Python :: 3.11
Classifier: Programming Language :: Python :: 3.12
Requires-Dist: datamodel-code-generator (>=0.22.1,<0.23.0)
Requires-Dist: docker (>=6.1.3,<7.0.0)
Requires-Dist: httpx (>=0.25.0,<0.26.0)
Requires-Dist: mergedeep (>=1.3.4,<2.0.0)
Requires-Dist: nwon_baseline (>=0.2.12,<0.3.0)
Requires-Dist: pydantic (>=2.0.0,<3.0.0)
Requires-Dist: toml (>=0.10.2,<0.11.0)
Project-URL: Repository, https://gitlab.com/nwon-group/nwon-tooling/pypi-packages/nwon-deployment
